setup.cfg
setup.py
chuda/__init__.py
chuda/app.py
chuda/arguments.py
chuda/commands.py
chuda/decorators.py
chuda/exceptions.py
chuda/logging.py
chuda/plugins.py
chuda/shell.py
chuda/utils.py
chuda.egg-info/PKG-INFO
chuda.egg-info/SOURCES.txt
chuda.egg-info/dependency_links.txt
chuda.egg-info/requires.txt
chuda.egg-info/top_level.txt