Metadata-Version: 1.1
Name: chuda
Version: 0.0.22
Summary: A simple framework to create CLI tools
Home-page: https://github.com/Varkal/chuda
Author: Romain Moreau
Author-email: moreau.romain83@gmail.com
License: MIT
Download-URL: https://github.com/Varkal/chuda/archive/0.0.22.tar.gz
Keywords: cli,chuda
Platform: UNKNOWN
Classifier: Development Status :: 2 - Pre-Alpha
Classifier: Environment :: Console
Classifier: Programming Language :: Python :: 3
